{"arraySize":5000000,"sortType":1,"parallelQuickSortTotalTime":305,"arraySortTotalTime":495,"totalMemoryConsumed":20,"gainInMilliseconds":190,"percentageGain":62.295081967213115,"ranOutOfMemoryDueToParallelQuickSort":false,"ranOutOfMemoryDueToArraysParallelSort":false}
{"arraySize":5000000,"sortType":1,"parallelQuickSortTotalTime":224,"arraySortTotalTime":455,"totalMemoryConsumed":19,"gainInMilliseconds":231,"percentageGain":103.125,"ranOutOfMemoryDueToParallelQuickSort":false,"ranOutOfMemoryDueToArraysParallelSort":false}
{"arraySize":5000000,"sortType":1,"parallelQuickSortTotalTime":206,"arraySortTotalTime":459,"totalMemoryConsumed":19,"gainInMilliseconds":253,"percentageGain":122.81553398058252,"ranOutOfMemoryDueToParallelQuickSort":false,"ranOutOfMemoryDueToArraysParallelSort":false}
{"arraySize":5000000,"sortType":1,"parallelQuickSortTotalTime":216,"arraySortTotalTime":461,"totalMemoryConsumed":19,"gainInMilliseconds":245,"percentageGain":113.42592592592592,"ranOutOfMemoryDueToParallelQuickSort":false,"ranOutOfMemoryDueToArraysParallelSort":false}
{"arraySize":5000000,"sortType":1,"parallelQuickSortTotalTime":210,"arraySortTotalTime":460,"totalMemoryConsumed":19,"gainInMilliseconds":250,"percentageGain":119.04761904761905,"ranOutOfMemoryDueToParallelQuickSort":false,"ranOutOfMemoryDueToArraysParallelSort":false}
{"arraySize":5000000,"sortType":1,"parallelQuickSortTotalTime":220,"arraySortTotalTime":456,"totalMemoryConsumed":19,"gainInMilliseconds":236,"percentageGain":107.27272727272728,"ranOutOfMemoryDueToParallelQuickSort":false,"ranOutOfMemoryDueToArraysParallelSort":false}
{"arraySize":5000000,"sortType":1,"parallelQuickSortTotalTime":225,"arraySortTotalTime":455,"totalMemoryConsumed":19,"gainInMilliseconds":230,"percentageGain":102.22222222222221,"ranOutOfMemoryDueToParallelQuickSort":false,"ranOutOfMemoryDueToArraysParallelSort":false}
{"arraySize":5000000,"sortType":1,"parallelQuickSortTotalTime":215,"arraySortTotalTime":456,"totalMemoryConsumed":19,"gainInMilliseconds":241,"percentageGain":112.09302325581396,"ranOutOfMemoryDueToParallelQuickSort":false,"ranOutOfMemoryDueToArraysParallelSort":false}
{"arraySize":5000000,"sortType":1,"parallelQuickSortTotalTime":199,"arraySortTotalTime":463,"totalMemoryConsumed":19,"gainInMilliseconds":264,"percentageGain":132.66331658291458,"ranOutOfMemoryDueToParallelQuickSort":false,"ranOutOfMemoryDueToArraysParallelSort":false}
{"arraySize":5000000,"sortType":1,"parallelQuickSortTotalTime":218,"arraySortTotalTime":462,"totalMemoryConsumed":19,"gainInMilliseconds":244,"percentageGain":111.92660550458714,"ranOutOfMemoryDueToParallelQuickSort":false,"ranOutOfMemoryDueToArraysParallelSort":false}
{"arraySize":5000000,"sortType":1,"parallelQuickSortTotalTime":200,"arraySortTotalTime":460,"totalMemoryConsumed":19,"gainInMilliseconds":260,"percentageGain":130.0,"ranOutOfMemoryDueToParallelQuickSort":false,"ranOutOfMemoryDueToArraysParallelSort":false}
{"arraySize":5000000,"sortType":1,"parallelQuickSortTotalTime":229,"arraySortTotalTime":453,"totalMemoryConsumed":19,"gainInMilliseconds":224,"percentageGain":97.81659388646288,"ranOutOfMemoryDueToParallelQuickSort":false,"ranOutOfMemoryDueToArraysParallelSort":false}
{"arraySize":5000000,"sortType":1,"parallelQuickSortTotalTime":232,"arraySortTotalTime":459,"totalMemoryConsumed":19,"gainInMilliseconds":227,"percentageGain":97.84482758620689,"ranOutOfMemoryDueToParallelQuickSort":false,"ranOutOfMemoryDueToArraysParallelSort":false}
{"arraySize":5000000,"sortType":1,"parallelQuickSortTotalTime":229,"arraySortTotalTime":455,"totalMemoryConsumed":19,"gainInMilliseconds":226,"percentageGain":98.68995633187772,"ranOutOfMemoryDueToParallelQuickSort":false,"ranOutOfMemoryDueToArraysParallelSort":false}
{"arraySize":5000000,"sortType":1,"parallelQuickSortTotalTime":214,"arraySortTotalTime":458,"totalMemoryConsumed":19,"gainInMilliseconds":244,"percentageGain":114.01869158878503,"ranOutOfMemoryDueToParallelQuickSort":false,"ranOutOfMemoryDueToArraysParallelSort":false}
{"arraySize":5000000,"sortType":1,"parallelQuickSortTotalTime":212,"arraySortTotalTime":487,"totalMemoryConsumed":19,"gainInMilliseconds":275,"percentageGain":129.7169811320755,"ranOutOfMemoryDueToParallelQuickSort":false,"ranOutOfMemoryDueToArraysParallelSort":false}
{"arraySize":5000000,"sortType":1,"parallelQuickSortTotalTime":211,"arraySortTotalTime":452,"totalMemoryConsumed":19,"gainInMilliseconds":241,"percentageGain":114.21800947867298,"ranOutOfMemoryDueToParallelQuickSort":false,"ranOutOfMemoryDueToArraysParallelSort":false}
{"arraySize":5000000,"sortType":1,"parallelQuickSortTotalTime":211,"arraySortTotalTime":459,"totalMemoryConsumed":19,"gainInMilliseconds":248,"percentageGain":117.53554502369667,"ranOutOfMemoryDueToParallelQuickSort":false,"ranOutOfMemoryDueToArraysParallelSort":false}
{"arraySize":5000000,"sortType":1,"parallelQuickSortTotalTime":205,"arraySortTotalTime":461,"totalMemoryConsumed":19,"gainInMilliseconds":256,"percentageGain":124.8780487804878,"ranOutOfMemoryDueToParallelQuickSort":false,"ranOutOfMemoryDueToArraysParallelSort":false}
{"arraySize":5000000,"sortType":1,"parallelQuickSortTotalTime":207,"arraySortTotalTime":458,"totalMemoryConsumed":19,"gainInMilliseconds":251,"percentageGain":121.256038647343,"ranOutOfMemoryDueToParallelQuickSort":false,"ranOutOfMemoryDueToArraysParallelSort":false}
{"arraySize":5000000,"sortType":1,"parallelQuickSortTotalTime":216,"arraySortTotalTime":458,"totalMemoryConsumed":19,"gainInMilliseconds":242,"percentageGain":112.03703703703705,"ranOutOfMemoryDueToParallelQuickSort":false,"ranOutOfMemoryDueToArraysParallelSort":false}
{"arraySize":5000000,"sortType":1,"parallelQuickSortTotalTime":207,"arraySortTotalTime":464,"totalMemoryConsumed":19,"gainInMilliseconds":257,"percentageGain":124.15458937198068,"ranOutOfMemoryDueToParallelQuickSort":false,"ranOutOfMemoryDueToArraysParallelSort":false}
{"arraySize":5000000,"sortType":1,"parallelQuickSortTotalTime":223,"arraySortTotalTime":454,"totalMemoryConsumed":19,"gainInMilliseconds":231,"percentageGain":103.58744394618836,"ranOutOfMemoryDueToParallelQuickSort":false,"ranOutOfMemoryDueToArraysParallelSort":false}
{"arraySize":5000000,"sortType":1,"parallelQuickSortTotalTime":208,"arraySortTotalTime":455,"totalMemoryConsumed":19,"gainInMilliseconds":247,"percentageGain":118.75,"ranOutOfMemoryDueToParallelQuickSort":false,"ranOutOfMemoryDueToArraysParallelSort":false}
{"arraySize":5000000,"sortType":1,"parallelQuickSortTotalTime":212,"arraySortTotalTime":459,"totalMemoryConsumed":19,"gainInMilliseconds":247,"percentageGain":116.50943396226414,"ranOutOfMemoryDueToParallelQuickSort":false,"ranOutOfMemoryDueToArraysParallelSort":false}
{"arraySize":5000000,"sortType":1,"parallelQuickSortTotalTime":211,"arraySortTotalTime":459,"totalMemoryConsumed":19,"gainInMilliseconds":248,"percentageGain":117.53554502369667,"ranOutOfMemoryDueToParallelQuickSort":false,"ranOutOfMemoryDueToArraysParallelSort":false}
{"arraySize":5000000,"sortType":1,"parallelQuickSortTotalTime":231,"arraySortTotalTime":473,"totalMemoryConsumed":19,"gainInMilliseconds":242,"percentageGain":104.76190476190477,"ranOutOfMemoryDueToParallelQuickSort":false,"ranOutOfMemoryDueToArraysParallelSort":false}
{"arraySize":5000000,"sortType":1,"parallelQuickSortTotalTime":204,"arraySortTotalTime":453,"totalMemoryConsumed":19,"gainInMilliseconds":249,"percentageGain":122.05882352941177,"ranOutOfMemoryDueToParallelQuickSort":false,"ranOutOfMemoryDueToArraysParallelSort":false}
{"arraySize":5000000,"sortType":1,"parallelQuickSortTotalTime":203,"arraySortTotalTime":458,"totalMemoryConsumed":19,"gainInMilliseconds":255,"percentageGain":125.61576354679802,"ranOutOfMemoryDueToParallelQuickSort":false,"ranOutOfMemoryDueToArraysParallelSort":false}
{"arraySize":5000000,"sortType":1,"parallelQuickSortTotalTime":212,"arraySortTotalTime":469,"totalMemoryConsumed":19,"gainInMilliseconds":257,"percentageGain":121.22641509433963,"ranOutOfMemoryDueToParallelQuickSort":false,"ranOutOfMemoryDueToArraysParallelSort":false}
{"arraySize":5000000,"sortType":1,"parallelQuickSortTotalTime":212,"arraySortTotalTime":456,"totalMemoryConsumed":19,"gainInMilliseconds":244,"percentageGain":115.09433962264151,"ranOutOfMemoryDueToParallelQuickSort":false,"ranOutOfMemoryDueToArraysParallelSort":false}
{"arraySize":5000000,"sortType":1,"parallelQuickSortTotalTime":195,"arraySortTotalTime":459,"totalMemoryConsumed":19,"gainInMilliseconds":264,"percentageGain":135.3846153846154,"ranOutOfMemoryDueToParallelQuickSort":false,"ranOutOfMemoryDueToArraysParallelSort":false}
{"arraySize":5000000,"sortType":1,"parallelQuickSortTotalTime":225,"arraySortTotalTime":456,"totalMemoryConsumed":19,"gainInMilliseconds":231,"percentageGain":102.66666666666666,"ranOutOfMemoryDueToParallelQuickSort":false,"ranOutOfMemoryDueToArraysParallelSort":false}
{"arraySize":5000000,"sortType":1,"parallelQuickSortTotalTime":205,"arraySortTotalTime":454,"totalMemoryConsumed":19,"gainInMilliseconds":249,"percentageGain":121.46341463414633,"ranOutOfMemoryDueToParallelQuickSort":false,"ranOutOfMemoryDueToArraysParallelSort":false}
{"arraySize":5000000,"sortType":1,"parallelQuickSortTotalTime":215,"arraySortTotalTime":456,"totalMemoryConsumed":19,"gainInMilliseconds":241,"percentageGain":112.09302325581396,"ranOutOfMemoryDueToParallelQuickSort":false,"ranOutOfMemoryDueToArraysParallelSort":false}
{"arraySize":5000000,"sortType":1,"parallelQuickSortTotalTime":207,"arraySortTotalTime":454,"totalMemoryConsumed":19,"gainInMilliseconds":247,"percentageGain":119.32367149758454,"ranOutOfMemoryDueToParallelQuickSort":false,"ranOutOfMemoryDueToArraysParallelSort":false}
{"arraySize":5000000,"sortType":1,"parallelQuickSortTotalTime":195,"arraySortTotalTime":459,"totalMemoryConsumed":19,"gainInMilliseconds":264,"percentageGain":135.3846153846154,"ranOutOfMemoryDueToParallelQuickSort":false,"ranOutOfMemoryDueToArraysParallelSort":false}
{"arraySize":5000000,"sortType":1,"parallelQuickSortTotalTime":209,"arraySortTotalTime":451,"totalMemoryConsumed":19,"gainInMilliseconds":242,"percentageGain":115.78947368421053,"ranOutOfMemoryDueToParallelQuickSort":false,"ranOutOfMemoryDueToArraysParallelSort":false}
{"arraySize":5000000,"sortType":1,"parallelQuickSortTotalTime":203,"arraySortTotalTime":453,"totalMemoryConsumed":19,"gainInMilliseconds":250,"percentageGain":123.15270935960592,"ranOutOfMemoryDueToParallelQuickSort":false,"ranOutOfMemoryDueToArraysParallelSort":false}
{"arraySize":5000000,"sortType":1,"parallelQuickSortTotalTime":217,"arraySortTotalTime":458,"totalMemoryConsumed":19,"gainInMilliseconds":241,"percentageGain":111.05990783410138,"ranOutOfMemoryDueToParallelQuickSort":false,"ranOutOfMemoryDueToArraysParallelSort":false}
{"arraySize":5000000,"sortType":1,"parallelQuickSortTotalTime":197,"arraySortTotalTime":453,"totalMemoryConsumed":19,"gainInMilliseconds":256,"percentageGain":129.9492385786802,"ranOutOfMemoryDueToParallelQuickSort":false,"ranOutOfMemoryDueToArraysParallelSort":false}
{"arraySize":5000000,"sortType":1,"parallelQuickSortTotalTime":194,"arraySortTotalTime":463,"totalMemoryConsumed":19,"gainInMilliseconds":269,"percentageGain":138.659793814433,"ranOutOfMemoryDueToParallelQuickSort":false,"ranOutOfMemoryDueToArraysParallelSort":false}
{"arraySize":5000000,"sortType":1,"parallelQuickSortTotalTime":215,"arraySortTotalTime":458,"totalMemoryConsumed":19,"gainInMilliseconds":243,"percentageGain":113.0232558139535,"ranOutOfMemoryDueToParallelQuickSort":false,"ranOutOfMemoryDueToArraysParallelSort":false}
{"arraySize":5000000,"sortType":1,"parallelQuickSortTotalTime":207,"arraySortTotalTime":456,"totalMemoryConsumed":19,"gainInMilliseconds":249,"percentageGain":120.28985507246377,"ranOutOfMemoryDueToParallelQuickSort":false,"ranOutOfMemoryDueToArraysParallelSort":false}
{"arraySize":5000000,"sortType":1,"parallelQuickSortTotalTime":192,"arraySortTotalTime":454,"totalMemoryConsumed":19,"gainInMilliseconds":262,"percentageGain":136.45833333333331,"ranOutOfMemoryDueToParallelQuickSort":false,"ranOutOfMemoryDueToArraysParallelSort":false}
{"arraySize":5000000,"sortType":1,"parallelQuickSortTotalTime":200,"arraySortTotalTime":451,"totalMemoryConsumed":19,"gainInMilliseconds":251,"percentageGain":125.49999999999999,"ranOutOfMemoryDueToParallelQuickSort":false,"ranOutOfMemoryDueToArraysParallelSort":false}
{"arraySize":5000000,"sortType":1,"parallelQuickSortTotalTime":196,"arraySortTotalTime":455,"totalMemoryConsumed":19,"gainInMilliseconds":259,"percentageGain":132.14285714285714,"ranOutOfMemoryDueToParallelQuickSort":false,"ranOutOfMemoryDueToArraysParallelSort":false}
{"arraySize":5000000,"sortType":1,"parallelQuickSortTotalTime":207,"arraySortTotalTime":463,"totalMemoryConsumed":19,"gainInMilliseconds":256,"percentageGain":123.67149758454106,"ranOutOfMemoryDueToParallelQuickSort":false,"ranOutOfMemoryDueToArraysParallelSort":false}
{"arraySize":5000000,"sortType":1,"parallelQuickSortTotalTime":218,"arraySortTotalTime":459,"totalMemoryConsumed":19,"gainInMilliseconds":241,"percentageGain":110.55045871559632,"ranOutOfMemoryDueToParallelQuickSort":false,"ranOutOfMemoryDueToArraysParallelSort":false}
{"arraySize":5000000,"sortType":1,"parallelQuickSortTotalTime":215,"arraySortTotalTime":455,"totalMemoryConsumed":19,"gainInMilliseconds":240,"percentageGain":111.62790697674419,"ranOutOfMemoryDueToParallelQuickSort":false,"ranOutOfMemoryDueToArraysParallelSort":false}
{"arraySize":5000000,"sortType":1,"parallelQuickSortTotalTime":201,"arraySortTotalTime":463,"totalMemoryConsumed":19,"gainInMilliseconds":262,"percentageGain":130.34825870646767,"ranOutOfMemoryDueToParallelQuickSort":false,"ranOutOfMemoryDueToArraysParallelSort":false}
{"arraySize":5000000,"sortType":1,"parallelQuickSortTotalTime":204,"arraySortTotalTime":456,"totalMemoryConsumed":19,"gainInMilliseconds":252,"percentageGain":123.52941176470588,"ranOutOfMemoryDueToParallelQuickSort":false,"ranOutOfMemoryDueToArraysParallelSort":false}
{"arraySize":5000000,"sortType":1,"parallelQuickSortTotalTime":200,"arraySortTotalTime":454,"totalMemoryConsumed":19,"gainInMilliseconds":254,"percentageGain":127.0,"ranOutOfMemoryDueToParallelQuickSort":false,"ranOutOfMemoryDueToArraysParallelSort":false}
{"arraySize":5000000,"sortType":1,"parallelQuickSortTotalTime":219,"arraySortTotalTime":455,"totalMemoryConsumed":19,"gainInMilliseconds":236,"percentageGain":107.76255707762556,"ranOutOfMemoryDueToParallelQuickSort":false,"ranOutOfMemoryDueToArraysParallelSort":false}
{"arraySize":5000000,"sortType":1,"parallelQuickSortTotalTime":214,"arraySortTotalTime":451,"totalMemoryConsumed":19,"gainInMilliseconds":237,"percentageGain":110.74766355140187,"ranOutOfMemoryDueToParallelQuickSort":false,"ranOutOfMemoryDueToArraysParallelSort":false}
{"arraySize":5000000,"sortType":1,"parallelQuickSortTotalTime":222,"arraySortTotalTime":458,"totalMemoryConsumed":19,"gainInMilliseconds":236,"percentageGain":106.30630630630631,"ranOutOfMemoryDueToParallelQuickSort":false,"ranOutOfMemoryDueToArraysParallelSort":false}
{"arraySize":5000000,"sortType":1,"parallelQuickSortTotalTime":211,"arraySortTotalTime":454,"totalMemoryConsumed":19,"gainInMilliseconds":243,"percentageGain":115.16587677725119,"ranOutOfMemoryDueToParallelQuickSort":false,"ranOutOfMemoryDueToArraysParallelSort":false}
{"arraySize":5000000,"sortType":1,"parallelQuickSortTotalTime":203,"arraySortTotalTime":459,"totalMemoryConsumed":19,"gainInMilliseconds":256,"percentageGain":126.10837438423646,"ranOutOfMemoryDueToParallelQuickSort":false,"ranOutOfMemoryDueToArraysParallelSort":false}
{"arraySize":5000000,"sortType":1,"parallelQuickSortTotalTime":218,"arraySortTotalTime":458,"totalMemoryConsumed":19,"gainInMilliseconds":240,"percentageGain":110.09174311926606,"ranOutOfMemoryDueToParallelQuickSort":false,"ranOutOfMemoryDueToArraysParallelSort":false}
{"arraySize":5000000,"sortType":1,"parallelQuickSortTotalTime":206,"arraySortTotalTime":459,"totalMemoryConsumed":19,"gainInMilliseconds":253,"percentageGain":122.81553398058252,"ranOutOfMemoryDueToParallelQuickSort":false,"ranOutOfMemoryDueToArraysParallelSort":false}
{"arraySize":5000000,"sortType":1,"parallelQuickSortTotalTime":220,"arraySortTotalTime":455,"totalMemoryConsumed":19,"gainInMilliseconds":235,"percentageGain":106.81818181818181,"ranOutOfMemoryDueToParallelQuickSort":false,"ranOutOfMemoryDueToArraysParallelSort":false}
{"arraySize":5000000,"sortType":1,"parallelQuickSortTotalTime":226,"arraySortTotalTime":453,"totalMemoryConsumed":19,"gainInMilliseconds":227,"percentageGain":100.44247787610618,"ranOutOfMemoryDueToParallelQuickSort":false,"ranOutOfMemoryDueToArraysParallelSort":false}
{"arraySize":5000000,"sortType":1,"parallelQuickSortTotalTime":206,"arraySortTotalTime":460,"totalMemoryConsumed":19,"gainInMilliseconds":254,"percentageGain":123.3009708737864,"ranOutOfMemoryDueToParallelQuickSort":false,"ranOutOfMemoryDueToArraysParallelSort":false}
{"arraySize":5000000,"sortType":1,"parallelQuickSortTotalTime":214,"arraySortTotalTime":459,"totalMemoryConsumed":19,"gainInMilliseconds":245,"percentageGain":114.48598130841121,"ranOutOfMemoryDueToParallelQuickSort":false,"ranOutOfMemoryDueToArraysParallelSort":false}
{"arraySize":5000000,"sortType":1,"parallelQuickSortTotalTime":214,"arraySortTotalTime":461,"totalMemoryConsumed":19,"gainInMilliseconds":247,"percentageGain":115.42056074766356,"ranOutOfMemoryDueToParallelQuickSort":false,"ranOutOfMemoryDueToArraysParallelSort":false}
{"arraySize":5000000,"sortType":1,"parallelQuickSortTotalTime":214,"arraySortTotalTime":497,"totalMemoryConsumed":19,"gainInMilliseconds":283,"percentageGain":132.2429906542056,"ranOutOfMemoryDueToParallelQuickSort":false,"ranOutOfMemoryDueToArraysParallelSort":false}
{"arraySize":5000000,"sortType":1,"parallelQuickSortTotalTime":244,"arraySortTotalTime":539,"totalMemoryConsumed":19,"gainInMilliseconds":295,"percentageGain":120.9016393442623,"ranOutOfMemoryDueToParallelQuickSort":false,"ranOutOfMemoryDueToArraysParallelSort":false}
{"arraySize":5000000,"sortType":1,"parallelQuickSortTotalTime":218,"arraySortTotalTime":457,"totalMemoryConsumed":19,"gainInMilliseconds":239,"percentageGain":109.63302752293578,"ranOutOfMemoryDueToParallelQuickSort":false,"ranOutOfMemoryDueToArraysParallelSort":false}
{"arraySize":5000000,"sortType":1,"parallelQuickSortTotalTime":220,"arraySortTotalTime":465,"totalMemoryConsumed":19,"gainInMilliseconds":245,"percentageGain":111.36363636363636,"ranOutOfMemoryDueToParallelQuickSort":false,"ranOutOfMemoryDueToArraysParallelSort":false}
{"arraySize":5000000,"sortType":1,"parallelQuickSortTotalTime":227,"arraySortTotalTime":488,"totalMemoryConsumed":19,"gainInMilliseconds":261,"percentageGain":114.97797356828194,"ranOutOfMemoryDueToParallelQuickSort":false,"ranOutOfMemoryDueToArraysParallelSort":false}
{"arraySize":5000000,"sortType":1,"parallelQuickSortTotalTime":204,"arraySortTotalTime":457,"totalMemoryConsumed":19,"gainInMilliseconds":253,"percentageGain":124.01960784313727,"ranOutOfMemoryDueToParallelQuickSort":false,"ranOutOfMemoryDueToArraysParallelSort":false}
{"arraySize":5000000,"sortType":1,"parallelQuickSortTotalTime":205,"arraySortTotalTime":459,"totalMemoryConsumed":19,"gainInMilliseconds":254,"percentageGain":123.90243902439025,"ranOutOfMemoryDueToParallelQuickSort":false,"ranOutOfMemoryDueToArraysParallelSort":false}
{"arraySize":5000000,"sortType":1,"parallelQuickSortTotalTime":197,"arraySortTotalTime":462,"totalMemoryConsumed":19,"gainInMilliseconds":265,"percentageGain":134.51776649746193,"ranOutOfMemoryDueToParallelQuickSort":false,"ranOutOfMemoryDueToArraysParallelSort":false}
{"arraySize":5000000,"sortType":1,"parallelQuickSortTotalTime":236,"arraySortTotalTime":517,"totalMemoryConsumed":19,"gainInMilliseconds":281,"percentageGain":119.06779661016948,"ranOutOfMemoryDueToParallelQuickSort":false,"ranOutOfMemoryDueToArraysParallelSort":false}
{"arraySize":5000000,"sortType":1,"parallelQuickSortTotalTime":259,"arraySortTotalTime":458,"totalMemoryConsumed":19,"gainInMilliseconds":199,"percentageGain":76.83397683397683,"ranOutOfMemoryDueToParallelQuickSort":false,"ranOutOfMemoryDueToArraysParallelSort":false}
{"arraySize":5000000,"sortType":1,"parallelQuickSortTotalTime":234,"arraySortTotalTime":674,"totalMemoryConsumed":19,"gainInMilliseconds":440,"percentageGain":188.03418803418802,"ranOutOfMemoryDueToParallelQuickSort":false,"ranOutOfMemoryDueToArraysParallelSort":false}
{"arraySize":5000000,"sortType":1,"parallelQuickSortTotalTime":219,"arraySortTotalTime":549,"totalMemoryConsumed":19,"gainInMilliseconds":330,"percentageGain":150.68493150684932,"ranOutOfMemoryDueToParallelQuickSort":false,"ranOutOfMemoryDueToArraysParallelSort":false}
{"arraySize":5000000,"sortType":1,"parallelQuickSortTotalTime":206,"arraySortTotalTime":509,"totalMemoryConsumed":19,"gainInMilliseconds":303,"percentageGain":147.0873786407767,"ranOutOfMemoryDueToParallelQuickSort":false,"ranOutOfMemoryDueToArraysParallelSort":false}
{"arraySize":5000000,"sortType":1,"parallelQuickSortTotalTime":224,"arraySortTotalTime":470,"totalMemoryConsumed":19,"gainInMilliseconds":246,"percentageGain":109.82142857142858,"ranOutOfMemoryDueToParallelQuickSort":false,"ranOutOfMemoryDueToArraysParallelSort":false}
{"arraySize":5000000,"sortType":1,"parallelQuickSortTotalTime":242,"arraySortTotalTime":466,"totalMemoryConsumed":19,"gainInMilliseconds":224,"percentageGain":92.56198347107438,"ranOutOfMemoryDueToParallelQuickSort":false,"ranOutOfMemoryDueToArraysParallelSort":false}
{"arraySize":5000000,"sortType":1,"parallelQuickSortTotalTime":204,"arraySortTotalTime":631,"totalMemoryConsumed":19,"gainInMilliseconds":427,"percentageGain":209.31372549019608,"ranOutOfMemoryDueToParallelQuickSort":false,"ranOutOfMemoryDueToArraysParallelSort":false}
{"arraySize":5000000,"sortType":1,"parallelQuickSortTotalTime":242,"arraySortTotalTime":503,"totalMemoryConsumed":19,"gainInMilliseconds":261,"percentageGain":107.85123966942149,"ranOutOfMemoryDueToParallelQuickSort":false,"ranOutOfMemoryDueToArraysParallelSort":false}
{"arraySize":5000000,"sortType":1,"parallelQuickSortTotalTime":239,"arraySortTotalTime":458,"totalMemoryConsumed":19,"gainInMilliseconds":219,"percentageGain":91.63179916317992,"ranOutOfMemoryDueToParallelQuickSort":false,"ranOutOfMemoryDueToArraysParallelSort":false}
{"arraySize":5000000,"sortType":1,"parallelQuickSortTotalTime":215,"arraySortTotalTime":469,"totalMemoryConsumed":19,"gainInMilliseconds":254,"percentageGain":118.13953488372093,"ranOutOfMemoryDueToParallelQuickSort":false,"ranOutOfMemoryDueToArraysParallelSort":false}
{"arraySize":5000000,"sortType":1,"parallelQuickSortTotalTime":213,"arraySortTotalTime":468,"totalMemoryConsumed":19,"gainInMilliseconds":255,"percentageGain":119.71830985915493,"ranOutOfMemoryDueToParallelQuickSort":false,"ranOutOfMemoryDueToArraysParallelSort":false}
{"arraySize":5000000,"sortType":1,"parallelQuickSortTotalTime":210,"arraySortTotalTime":481,"totalMemoryConsumed":19,"gainInMilliseconds":271,"percentageGain":129.04761904761907,"ranOutOfMemoryDueToParallelQuickSort":false,"ranOutOfMemoryDueToArraysParallelSort":false}
{"arraySize":5000000,"sortType":1,"parallelQuickSortTotalTime":211,"arraySortTotalTime":452,"totalMemoryConsumed":19,"gainInMilliseconds":241,"percentageGain":114.21800947867298,"ranOutOfMemoryDueToParallelQuickSort":false,"ranOutOfMemoryDueToArraysParallelSort":false}
{"arraySize":5000000,"sortType":1,"parallelQuickSortTotalTime":220,"arraySortTotalTime":453,"totalMemoryConsumed":19,"gainInMilliseconds":233,"percentageGain":105.9090909090909,"ranOutOfMemoryDueToParallelQuickSort":false,"ranOutOfMemoryDueToArraysParallelSort":false}
{"arraySize":5000000,"sortType":1,"parallelQuickSortTotalTime":207,"arraySortTotalTime":456,"totalMemoryConsumed":19,"gainInMilliseconds":249,"percentageGain":120.28985507246377,"ranOutOfMemoryDueToParallelQuickSort":false,"ranOutOfMemoryDueToArraysParallelSort":false}
{"arraySize":5000000,"sortType":1,"parallelQuickSortTotalTime":208,"arraySortTotalTime":454,"totalMemoryConsumed":19,"gainInMilliseconds":246,"percentageGain":118.26923076923077,"ranOutOfMemoryDueToParallelQuickSort":false,"ranOutOfMemoryDueToArraysParallelSort":false}
{"arraySize":5000000,"sortType":1,"parallelQuickSortTotalTime":193,"arraySortTotalTime":459,"totalMemoryConsumed":19,"gainInMilliseconds":266,"percentageGain":137.8238341968912,"ranOutOfMemoryDueToParallelQuickSort":false,"ranOutOfMemoryDueToArraysParallelSort":false}
{"arraySize":5000000,"sortType":1,"parallelQuickSortTotalTime":221,"arraySortTotalTime":456,"totalMemoryConsumed":19,"gainInMilliseconds":235,"percentageGain":106.33484162895928,"ranOutOfMemoryDueToParallelQuickSort":false,"ranOutOfMemoryDueToArraysParallelSort":false}
{"arraySize":5000000,"sortType":1,"parallelQuickSortTotalTime":224,"arraySortTotalTime":458,"totalMemoryConsumed":19,"gainInMilliseconds":234,"percentageGain":104.46428571428572,"ranOutOfMemoryDueToParallelQuickSort":false,"ranOutOfMemoryDueToArraysParallelSort":false}
{"arraySize":5000000,"sortType":1,"parallelQuickSortTotalTime":221,"arraySortTotalTime":456,"totalMemoryConsumed":19,"gainInMilliseconds":235,"percentageGain":106.33484162895928,"ranOutOfMemoryDueToParallelQuickSort":false,"ranOutOfMemoryDueToArraysParallelSort":false}
{"arraySize":5000000,"sortType":1,"parallelQuickSortTotalTime":202,"arraySortTotalTime":459,"totalMemoryConsumed":19,"gainInMilliseconds":257,"percentageGain":127.22772277227723,"ranOutOfMemoryDueToParallelQuickSort":false,"ranOutOfMemoryDueToArraysParallelSort":false}
{"arraySize":5000000,"sortType":1,"parallelQuickSortTotalTime":198,"arraySortTotalTime":459,"totalMemoryConsumed":19,"gainInMilliseconds":261,"percentageGain":131.8181818181818,"ranOutOfMemoryDueToParallelQuickSort":false,"ranOutOfMemoryDueToArraysParallelSort":false}
{"arraySize":5000000,"sortType":1,"parallelQuickSortTotalTime":202,"arraySortTotalTime":451,"totalMemoryConsumed":19,"gainInMilliseconds":249,"percentageGain":123.26732673267327,"ranOutOfMemoryDueToParallelQuickSort":false,"ranOutOfMemoryDueToArraysParallelSort":false}
{"arraySize":5000000,"sortType":1,"parallelQuickSortTotalTime":211,"arraySortTotalTime":458,"totalMemoryConsumed":19,"gainInMilliseconds":247,"percentageGain":117.06161137440758,"ranOutOfMemoryDueToParallelQuickSort":false,"ranOutOfMemoryDueToArraysParallelSort":false}
{"arraySize":5000000,"sortType":1,"parallelQuickSortTotalTime":206,"arraySortTotalTime":455,"totalMemoryConsumed":19,"gainInMilliseconds":249,"percentageGain":120.87378640776699,"ranOutOfMemoryDueToParallelQuickSort":false,"ranOutOfMemoryDueToArraysParallelSort":false}
{"arraySize":5000000,"sortType":1,"parallelQuickSortTotalTime":199,"arraySortTotalTime":458,"totalMemoryConsumed":19,"gainInMilliseconds":259,"percentageGain":130.15075376884423,"ranOutOfMemoryDueToParallelQuickSort":false,"ranOutOfMemoryDueToArraysParallelSort":false}
