{"arraySize":100000000,"sortType":1,"parallelQuickSortTotalTime":4824,"arraySortTotalTime":10939,"totalMemoryConsumed":382,"gainInMilliseconds":6115,"percentageGain":126.7620232172471,"ranOutOfMemoryDueToParallelQuickSort":false,"ranOutOfMemoryDueToArraysParallelSort":false}
{"arraySize":100000000,"sortType":1,"parallelQuickSortTotalTime":5173,"arraySortTotalTime":11654,"totalMemoryConsumed":382,"gainInMilliseconds":6481,"percentageGain":125.28513435144018,"ranOutOfMemoryDueToParallelQuickSort":false,"ranOutOfMemoryDueToArraysParallelSort":false}
{"arraySize":100000000,"sortType":1,"parallelQuickSortTotalTime":4664,"arraySortTotalTime":10852,"totalMemoryConsumed":382,"gainInMilliseconds":6188,"percentageGain":132.67581475128645,"ranOutOfMemoryDueToParallelQuickSort":false,"ranOutOfMemoryDueToArraysParallelSort":false}
{"arraySize":100000000,"sortType":1,"parallelQuickSortTotalTime":4917,"arraySortTotalTime":11047,"totalMemoryConsumed":382,"gainInMilliseconds":6130,"percentageGain":124.66951393125889,"ranOutOfMemoryDueToParallelQuickSort":false,"ranOutOfMemoryDueToArraysParallelSort":false}
{"arraySize":100000000,"sortType":1,"parallelQuickSortTotalTime":5846,"arraySortTotalTime":10924,"totalMemoryConsumed":382,"gainInMilliseconds":5078,"percentageGain":86.86281217926788,"ranOutOfMemoryDueToParallelQuickSort":false,"ranOutOfMemoryDueToArraysParallelSort":false}
{"arraySize":100000000,"sortType":1,"parallelQuickSortTotalTime":5027,"arraySortTotalTime":11501,"totalMemoryConsumed":382,"gainInMilliseconds":6474,"percentageGain":128.7845633578675,"ranOutOfMemoryDueToParallelQuickSort":false,"ranOutOfMemoryDueToArraysParallelSort":false}
{"arraySize":100000000,"sortType":1,"parallelQuickSortTotalTime":4834,"arraySortTotalTime":10894,"totalMemoryConsumed":382,"gainInMilliseconds":6060,"percentageGain":125.36201903185768,"ranOutOfMemoryDueToParallelQuickSort":false,"ranOutOfMemoryDueToArraysParallelSort":false}
{"arraySize":100000000,"sortType":1,"parallelQuickSortTotalTime":5159,"arraySortTotalTime":10964,"totalMemoryConsumed":382,"gainInMilliseconds":5805,"percentageGain":112.52180655165729,"ranOutOfMemoryDueToParallelQuickSort":false,"ranOutOfMemoryDueToArraysParallelSort":false}
{"arraySize":100000000,"sortType":1,"parallelQuickSortTotalTime":4863,"arraySortTotalTime":10829,"totalMemoryConsumed":382,"gainInMilliseconds":5966,"percentageGain":122.68147234217561,"ranOutOfMemoryDueToParallelQuickSort":false,"ranOutOfMemoryDueToArraysParallelSort":false}
{"arraySize":100000000,"sortType":1,"parallelQuickSortTotalTime":4705,"arraySortTotalTime":10765,"totalMemoryConsumed":382,"gainInMilliseconds":6060,"percentageGain":128.7991498405951,"ranOutOfMemoryDueToParallelQuickSort":false,"ranOutOfMemoryDueToArraysParallelSort":false}
