{"arraySize":200000000,"sortType":1,"parallelQuickSortTotalTime":7949,"arraySortTotalTime":33461,"totalMemoryConsumed":768,"gainInMilliseconds":25512,"percentageGain":320.94603094728893,"ranOutOfMemoryDueToParallelQuickSort":false,"ranOutOfMemoryDueToArraysParallelSort":false}
{"arraySize":200000000,"sortType":1,"parallelQuickSortTotalTime":10208,"arraySortTotalTime":33756,"totalMemoryConsumed":763,"gainInMilliseconds":23548,"percentageGain":230.68181818181816,"ranOutOfMemoryDueToParallelQuickSort":false,"ranOutOfMemoryDueToArraysParallelSort":false}
{"arraySize":200000000,"sortType":1,"parallelQuickSortTotalTime":9782,"arraySortTotalTime":33658,"totalMemoryConsumed":764,"gainInMilliseconds":23876,"percentageGain":244.08096503782457,"ranOutOfMemoryDueToParallelQuickSort":false,"ranOutOfMemoryDueToArraysParallelSort":false}
{"arraySize":200000000,"sortType":1,"parallelQuickSortTotalTime":8864,"arraySortTotalTime":33694,"totalMemoryConsumed":764,"gainInMilliseconds":24830,"percentageGain":280.1218411552346,"ranOutOfMemoryDueToParallelQuickSort":false,"ranOutOfMemoryDueToArraysParallelSort":false}
{"arraySize":200000000,"sortType":1,"parallelQuickSortTotalTime":8906,"arraySortTotalTime":33698,"totalMemoryConsumed":764,"gainInMilliseconds":24792,"percentageGain":278.37412980013477,"ranOutOfMemoryDueToParallelQuickSort":false,"ranOutOfMemoryDueToArraysParallelSort":false}
